["Controls","dropdown",{"dropdown gender=male":[{"value":"male","text":"Male"},{"value":"female","text":"Female"}]}]
["Charts","bar chart",{"bar chart":{"columns":[["Apples",3],["Oranges",2],["Pears",2]]}}]
["Charts","donut chart",{"donut chart":{"columns":[["Apples",3],["Oranges",2],["Pears",2]]}}]
["Charts","pie chart",{"pie chart":{"columns":[["Apples",3],["Oranges",2],["Pears",2]]}}]
["Charts","stacked bar chart",{"stacked bar chart":{"columns":[["Apples",3,2,3,4,2],["Oranges",2,1,0,1,1],["Pears",2,0,0,3,4]]}}]
["Charts","stacked line chart",{"stacked line chart":{"columns":[["Apples",3,2,3,4,2],["Oranges",2,1,0,1,1],["Pears",2,0,0,3,4]]}}]
["Charts","stacked spline chart",{"stacked spline chart":{"columns":[["Apples",3,2,3,4,2],["Oranges",2,1,0,1,1],["Pears",2,0,0,3,4]]}}]
["Charts","stacked area chart",{"stacked area chart":{"columns":[["Apples",3,2,3,4,2],["Oranges",2,1,0,1,1],["Pears",2,0,0,3,4]]}}]
["Charts","gauge chart",{"gauge chart":{"columns":[["data",30]]}}]
["Charts","scatter chart",{"scatter plot":{"xs":{"setosa":"setosa_x","versicolor":"versicolor_x"},"columns":[["setosa_x",3.5,3,3.2,3.1,3.6,3.9,3.4,3.4,2.9,3.1,3.7,3.4,3,3,4,4.4,3.9,3.5,3.8,3.8,3.4,3.7,3.6,3.3,3.4,3,3.4,3.5,3.4,3.2,3.1,3.4,4.1,4.2,3.1,3.2,3.5,3.6,3,3.4,3.5,2.3,3.2,3.5,3.8,3,3.8,3.2,3.7,3.3],["versicolor_x",3.2,3.2,3.1,2.3,2.8,2.8,3.3,2.4,2.9,2.7,2,3,2.2,2.9,2.9,3.1,3,2.7,2.2,2.5,3.2,2.8,2.5,2.8,2.9,3,2.8,3,2.9,2.6,2.4,2.4,2.7,2.7,3,3.4,3.1,2.3,3,2.5,2.6,3,2.6,2.3,2.7,3,2.9,2.9,2.5,2.8],["setosa",0.2,0.2,0.2,0.2,0.2,0.4,0.3,0.2,0.2,0.1,0.2,0.2,0.1,0.1,0.2,0.4,0.4,0.3,0.3,0.3,0.2,0.4,0.2,0.5,0.2,0.2,0.4,0.2,0.2,0.2,0.2,0.4,0.1,0.2,0.2,0.2,0.2,0.1,0.2,0.2,0.3,0.3,0.2,0.6,0.4,0.3,0.2,0.2,0.2,0.2],["versicolor",1.4,1.5,1.5,1.3,1.5,1.3,1.6,1,1.3,1.4,1,1.5,1,1.4,1.3,1.4,1.5,1,1.5,1.1,1.8,1.3,1.5,1.2,1.3,1.4,1.4,1.7,1.5,1,1.1,1,1.2,1.6,1.5,1.6,1.5,1.3,1.3,1.3,1.2,1.4,1.2,1,1.3,1.2,1.3,1.3,1.1,1.3]]}}]
["Charts","line chart",{"line chart":{"columns":[["Apples",30,29,25,26,27,10],["Oranges",20,21,22,20,27,19],["Pears",10,9,8,8,7,8]]}}]
["Charts","bubble chart",{"bubble chart":{"columns":[["Apples",30,29,25,26,27,10],["Oranges",20,21,22,20,27,19],["Pears",10,9,8,8,7,8]]}}]
["Charts","spline chart",{"spline chart":{"columns":[["Apples",30,29,25,26,27,10],["Oranges",20,21,22,20,27,19],["Pears",10,9,8,8,7,8]]}}]
["Charts","area chart",{"area chart":{"columns":[["Apples",30,29,25,26,27,10],["Oranges",20,21,22,20,27,19]]}}]
["Charts","step chart",{"step chart":{"columns":[["Apples",30,29,25,26,27,10],["Oranges",20,21,22,20,27,19]]}}]
["Grid","columns",{"2 columns":[{"pie chart":{"columns":[["Apples",3],["Oranges",2],["Pears",2]]}},{"p text":"Lorem ipsum dolor sit amet, consectetur adipiscing elit. Etiam dolor massa, luctus rhoncus justo vel, cursus placerat ligula. Proin pulvinar ipsum in enim rutrum, quis fermentum ex finibus. Nunc commodo urna tellus, tristique tempor magna tempor eget. Phasellus eu ex lacinia sapien viverra fermentum."}]}]
["Text","h1 text",{"h1 text":"Lorem ipsum dolor sit amet"}]
["Text","h2 text",{"h2 text":"Lorem ipsum dolor sit amet"}]
["Text","h3 text",{"h3 text":"Lorem ipsum dolor sit amet"}]
["Text","p text",{"p text":"Lorem ipsum dolor sit amet"}]
["Grid","rows",{"2 columns":[{"rows":[{"h2 text":"Lorem ipsum dolor sit amet"},{"pie chart":{"columns":[["Apples",3],["Oranges",2],["Pears",2]]}}]},{"rows":[{"h2 text":"Lorem ipsum dolor sit amet"},{"p text":"Lorem ipsum dolor sit amet, consectetur adipiscing elit. Etiam dolor massa, luctus rhoncus justo vel, cursus placerat ligula. Proin pulvinar ipsum in enim rutrum, quis fermentum ex finibus. Nunc commodo urna tellus, tristique tempor magna tempor eget. Phasellus eu ex lacinia sapien viverra fermentum."}]}]}]
